Workbook

Sheet Dashboard
B2: Total Revenue | F2: Total Expenses | J2: Net Profit | N2: Total Invoices | R2: Accounts Receivable | V2: Accounts Payable
B3: =Summary!C9 -> 16279958 | F3: =Summary!D9 -> 8467926.9 | J3: =Summary!E9 -> 7812031.3 | N3: =Summary!F9 -> 1000 | R3: =Summary!G9 -> 5731832.7 | V3: =Summary!H9 -> 2839559.5
B21: Monthly Summary
B22: Month | D22: Revenue (₹) | F22: Expenses (₹) | H22: Net Profit (₹) | J22: Invoices | L22: AR (₹) | N22: AP (₹)
B23: =Summary!B3 -> Jan | D23: =Summary!C3 -> 3354465.5 | F23: =Summary!D3 -> 1236861.3 | H23: =Summary!E3 -> 2117604.2 | J23: =Summary!F3 -> 171 | L23: =Summary!G3 -> 1093087.2 | N23: =Summary!H3 -> 439339.46
B24: =Summary!B4 -> Feb | D24: =Summary!C4 -> 2432851 | F24: =Summary!D4 -> 1391774.6 | H24: =Summary!E4 -> 1041076.4 | J24: =Summary!F4 -> 150 | L24: =Summary!G4 -> 1099647.1 | N24: =Summary!H4 -> 477762.05
B25: =Summary!B5 -> Mar | D25: =Summary!C5 -> 2490507.5 | F25: =Summary!D5 -> 1686020.1 | H25: =Summary!E5 -> 804487.37 | J25: =Summary!F5 -> 186 | L25: =Summary!G5 -> 797709.58 | N25: =Summary!H5 -> 535581.95
B26: =Summary!B6 -> Apr | D26: =Summary!C6 -> 2680684.2 | F26: =Summary!D6 -> 1432062.2 | H26: =Summary!E6 -> 1248622 | J26: =Summary!F6 -> 158 | L26: =Summary!G6 -> 814908.83 | N26: =Summary!H6 -> 522252.45
B27: =Summary!B7 -> May | D27: =Summary!C7 -> 2449121.2 | F27: =Summary!D7 -> 1394173.7 | H27: =Summary!E7 -> 1054947.5 | J27: =Summary!F7 -> 167 | L27: =Summary!G7 -> 583980.97 | N27: =Summary!H7 -> 390102.61
B28: =Summary!B8 -> Jun | D28: =Summary!C8 -> 2872328.9 | F28: =Summary!D8 -> 1327035.1 | H28: =Summary!E8 -> 1545293.8 | J28: =Summary!F8 -> 168 | L28: =Summary!G8 -> 1342499 | N28: =Summary!H8 -> 474521.01
B29: =Summary!B9 -> Total | D29: =Summary!C9 -> 16279958 | F29: =Summary!D9 -> 8467926.9 | H29: =Summary!E9 -> 7812031.3 | J29: =Summary!F9 -> 1000 | L29: =Summary!G9 -> 5731832.7 | N29: =Summary!H9 -> 2839559.5

Sheet Summary
B2: Month | C2: Revenue | D2: Expense | E2: Net Profit | F2: Invoices | G2: AR | H2: AP
B3: Jan | C3: =SUMIFS('Raw Data'!F:F, 'Raw Data'!C:C, B3, 'Raw Data'!D:D, "Revenue") -> 3354465.5 | D3: =SUMIFS('Raw Data'!F:F, 'Raw Data'!C:C, B3, 'Raw Data'!D:D, "Expense") -> 1236861.3 | E3: =C3-D3 -> 2117604.2 | F3: =COUNTIFS('Raw Data'!C:C, B3) -> 171 | G3: =SUMIFS('Raw Data'!F:F, 'Raw Data'!C:C, B3, 'Raw Data'!D:D, "Revenue", 'Raw Data'!G:G, "Pending") + SUMIFS('Raw Data'!F:F, 'Raw Data'!C:C, B3, 'Raw Data'!D:D, "Revenue", 'Raw Data'!G:G, "Overdue") -> 1093087.2 | H3: =SUMIFS('Raw Data'!F:F, 'Raw Data'!C:C, B3, 'Raw Data'!D:D, "Expense", 'Raw Data'!G:G, "Pending") + SUMIFS('Raw Data'!F:F, 'Raw Data'!C:C, B3, 'Raw Data'!D:D, "Expense", 'Raw Data'!G:G, "Overdue") -> 439339.46
B4: Feb | C4: =SUMIFS('Raw Data'!F:F, 'Raw Data'!C:C, B4, 'Raw Data'!D:D, "Revenue") -> 2432851 | D4: =SUMIFS('Raw Data'!F:F, 'Raw Data'!C:C, B4, 'Raw Data'!D:D, "Expense") -> 1391774.6 | E4: =C4-D4 -> 1041076.4 | F4: =COUNTIFS('Raw Data'!C:C, B4) -> 150 | G4: =SUMIFS('Raw Data'!F:F, 'Raw Data'!C:C, B4, 'Raw Data'!D:D, "Revenue", 'Raw Data'!G:G, "Pending") + SUMIFS('Raw Data'!F:F, 'Raw Data'!C:C, B4, 'Raw Data'!D:D, "Revenue", 'Raw Data'!G:G, "Overdue") -> 1099647.1 | H4: =SUMIFS('Raw Data'!F:F, 'Raw Data'!C:C, B4, 'Raw Data'!D:D, "Expense", 'Raw Data'!G:G, "Pending") + SUMIFS('Raw Data'!F:F, 'Raw Data'!C:C, B4, 'Raw Data'!D:D, "Expense", 'Raw Data'!G:G, "Overdue") -> 477762.05
B5: Mar | C5: =SUMIFS('Raw Data'!F:F, 'Raw Data'!C:C, B5, 'Raw Data'!D:D, "Revenue") -> 2490507.5 | D5: =SUMIFS('Raw Data'!F:F, 'Raw Data'!C:C, B5, 'Raw Data'!D:D, "Expense") -> 1686020.1 | E5: =C5-D5 -> 804487.37 | F5: =COUNTIFS('Raw Data'!C:C, B5) -> 186 | G5: =SUMIFS('Raw Data'!F:F, 'Raw Data'!C:C, B5, 'Raw Data'!D:D, "Revenue", 'Raw Data'!G:G, "Pending") + SUMIFS('Raw Data'!F:F, 'Raw Data'!C:C, B5, 'Raw Data'!D:D, "Revenue", 'Raw Data'!G:G, "Overdue") -> 797709.58 | H5: =SUMIFS('Raw Data'!F:F, 'Raw Data'!C:C, B5, 'Raw Data'!D:D, "Expense", 'Raw Data'!G:G, "Pending") + SUMIFS('Raw Data'!F:F, 'Raw Data'!C:C, B5, 'Raw Data'!D:D, "Expense", 'Raw Data'!G:G, "Overdue") -> 535581.95
B6: Apr | C6: =SUMIFS('Raw Data'!F:F, 'Raw Data'!C:C, B6, 'Raw Data'!D:D, "Revenue") -> 2680684.2 | D6: =SUMIFS('Raw Data'!F:F, 'Raw Data'!C:C, B6, 'Raw Data'!D:D, "Expense") -> 1432062.2 | E6: =C6-D6 -> 1248622 | F6: =COUNTIFS('Raw Data'!C:C, B6) -> 158 | G6: =SUMIFS('Raw Data'!F:F, 'Raw Data'!C:C, B6, 'Raw Data'!D:D, "Revenue", 'Raw Data'!G:G, "Pending") + SUMIFS('Raw Data'!F:F, 'Raw Data'!C:C, B6, 'Raw Data'!D:D, "Revenue", 'Raw Data'!G:G, "Overdue") -> 814908.83 | H6: =SUMIFS('Raw Data'!F:F, 'Raw Data'!C:C, B6, 'Raw Data'!D:D, "Expense", 'Raw Data'!G:G, "Pending") + SUMIFS('Raw Data'!F:F, 'Raw Data'!C:C, B6, 'Raw Data'!D:D, "Expense", 'Raw Data'!G:G, "Overdue") -> 522252.45
B7: May | C7: =SUMIFS('Raw Data'!F:F, 'Raw Data'!C:C, B7, 'Raw Data'!D:D, "Revenue") -> 2449121.2 | D7: =SUMIFS('Raw Data'!F:F, 'Raw Data'!C:C, B7, 'Raw Data'!D:D, "Expense") -> 1394173.7 | E7: =C7-D7 -> 1054947.5 | F7: =COUNTIFS('Raw Data'!C:C, B7) -> 167 | G7: =SUMIFS('Raw Data'!F:F, 'Raw Data'!C:C, B7, 'Raw Data'!D:D, "Revenue", 'Raw Data'!G:G, "Pending") + SUMIFS('Raw Data'!F:F, 'Raw Data'!C:C, B7, 'Raw Data'!D:D, "Revenue", 'Raw Data'!G:G, "Overdue") -> 583980.97 | H7: =SUMIFS('Raw Data'!F:F, 'Raw Data'!C:C, B7, 'Raw Data'!D:D, "Expense", 'Raw Data'!G:G, "Pending") + SUMIFS('Raw Data'!F:F, 'Raw Data'!C:C, B7, 'Raw Data'!D:D, "Expense", 'Raw Data'!G:G, "Overdue") -> 390102.61
B8: Jun | C8: =SUMIFS('Raw Data'!F:F, 'Raw Data'!C:C, B8, 'Raw Data'!D:D, "Revenue") -> 2872328.9 | D8: =SUMIFS('Raw Data'!F:F, 'Raw Data'!C:C, B8, 'Raw Data'!D:D, "Expense") -> 1327035.1 | E8: =C8-D8 -> 1545293.8 | F8: =COUNTIFS('Raw Data'!C:C, B8) -> 168 | G8: =SUMIFS('Raw Data'!F:F, 'Raw Data'!C:C, B8, 'Raw Data'!D:D, "Revenue", 'Raw Data'!G:G, "Pending") + SUMIFS('Raw Data'!F:F, 'Raw Data'!C:C, B8, 'Raw Data'!D:D, "Revenue", 'Raw Data'!G:G, "Overdue") -> 1342499 | H8: =SUMIFS('Raw Data'!F:F, 'Raw Data'!C:C, B8, 'Raw Data'!D:D, "Expense", 'Raw Data'!G:G, "Pending") + SUMIFS('Raw Data'!F:F, 'Raw Data'!C:C, B8, 'Raw Data'!D:D, "Expense", 'Raw Data'!G:G, "Overdue") -> 474521.01
B9: Total | C9: =SUM(C3:C8) -> 16279958 | D9: =SUM(D3:D8) -> 8467926.9 | E9: =SUM(E3:E8) -> 7812031.3 | F9: =SUM(F3:F8) -> 1000 | G9: =SUM(G3:G8) -> 5731832.7 | H9: =SUM(H3:H8) -> 2839559.5
B11: Expense Category | C11: Amount
B12: Raw Material | C12: =SUMIFS('Raw Data'!F:F, 'Raw Data'!E:E, B12) -> 2934728.7
B13: Employee Cost | C13: =SUMIFS('Raw Data'!F:F, 'Raw Data'!E:E, B13) -> 1811743.8
B14: Utilities | C14: =SUMIFS('Raw Data'!F:F, 'Raw Data'!E:E, B14) -> 1486970.4
B15: Logistics | C15: =SUMIFS('Raw Data'!F:F, 'Raw Data'!E:E, B15) -> 855745.51
B16: Other Expenses | C16: =SUMIFS('Raw Data'!F:F, 'Raw Data'!E:E, B16) -> 1378738.6
B18: Invoice Status | C18: Count
B19: Paid | C19: =COUNTIFS('Raw Data'!G:G, B19) -> 652
B20: Pending | C20: =COUNTIFS('Raw Data'!G:G, B20) -> 256
B21: Overdue | C21: =COUNTIFS('Raw Data'!G:G, B21) -> 92

Sheet Raw Data
A1: Invoice ID | B1: Date | C1: Month | D1: Type | E1: Category | F1: Amount | G1: Invoice Status
A2: INV-1001 | B2: 45292 | C2: Jan | D2: Expense | E2: Raw Material | F2: 7170.62 | G2: Paid
A3: INV-1002 | B3: 45292 | C3: Jan | D3: Expense | E3: Employee Cost | F3: 5426.76 | G3: Paid
A4: INV-1003 | B4: 45292 | C4: Jan | D4: Expense | E4: Other Expenses | F4: 8109.55 | G4: Paid
A5: INV-1004 | B5: 45292 | C5: Jan | D5: Expense | E5: Utilities | F5: 5271.43 | G5: Overdue
A6: INV-1005 | B6: 45292 | C6: Jan | D6: Revenue | E6: Sales | F6: 14174.66 | G6: Overdue
A7: INV-1006 | B7: 45292 | C7: Jan | D7: Revenue | E7: Sales | F7: 65484 | G7: Paid
A8: INV-1007 | B8: 45292 | C8: Jan | D8: Revenue | E8: Sales | F8: 51653.08 | G8: Pending
A9: INV-1008 | B9: 45293 | C9: Jan | D9: Expense | E9: Logistics | F9: 20957.53 | G9: Paid
A10: INV-1009 | B10: 45293 | C10: Jan | D10: Expense | E10: Utilities | F10: 23187.43 | G10: Paid
A11: INV-1010 | B11: 45293 | C11: Jan | D11: Expense | E11: Utilities | F11: 12100.53 | G11: Paid
A12: INV-1011 | B12: 45293 | C12: Jan | D12: Revenue | E12: Sales | F12: 42808.86 | G12: Pending
A13: INV-1012 | B13: 45294 | C13: Jan | D13: Expense | E13: Logistics | F13: 8994.1 | G13: Paid
... A1001: INV-2000 | B1001: 45473 | C1001: Jun | D1001: Expense | E1001: Other Expenses | F1001: 13944.65 | G1001: Pending
A1002: Total | F1002: =SUM(F2:F1001) -> 24747885
